<annotation>
	<folder>plant images</folder>
	<filename>60.jpg</filename>
	<path>/Users/arnoleninmalyala/Documents/Alekhya/Special_Topics/Project_Data/plant images/60.jpg</path>
	<source>
		<database>Unknown</database>
	</source>
	<size>
		<width>500</width>
		<height>647</height>
		<depth>3</depth>
	</size>
	<segmented>0</segmented>
	<object>
		<name>plants</name>
		<pose>Unspecified</pose>
		<truncated>1</truncated>
		<difficult>0</difficult>
		<bndbox>
			<xmin>1</xmin>
			<ymin>1</ymin>
			<xmax>492</xmax>
			<ymax>588</ymax>
		</bndbox>
	</object>
</annotation>
